CHANGES.md
MANIFEST.in
README.md
pyproject.toml
setup.cfg
setup.py
src/data_flow_diagram/__init__.py
src/data_flow_diagram/config.py
src/data_flow_diagram/dependency_checker.py
src/data_flow_diagram/dfd.py
src/data_flow_diagram/dfd_dot_templates.py
src/data_flow_diagram/dot.py
src/data_flow_diagram/error.py
src/data_flow_diagram/markdown.py
src/data_flow_diagram/model.py
src/data_flow_diagram/parser.py
src/data_flow_diagram/scanner.py
src/data_flow_diagram.egg-info/PKG-INFO
src/data_flow_diagram.egg-info/SOURCES.txt
src/data_flow_diagram.egg-info/dependency_links.txt
src/data_flow_diagram.egg-info/entry_points.txt
src/data_flow_diagram.egg-info/requires.txt
src/data_flow_diagram.egg-info/top_level.txt