Metadata-Version: 2.2
Name: data-flow-diagram
Version: 1.12.1.post3
Summary: Commandline tool to generate data flow diagrams from text
Home-page: https://github.com/pbauermeister/dfd
Author: Pascal Bauermeister
Author-email: pascal.bauermeister@gmail.com
License: GNU General Public License v3 (GPLv3)
Project-URL: Bug Reports, https://github.com/pbauermeister/dfd/issues
Project-URL: Source, https://github.com/pbauermeister/dfd
Keywords: diagram-generator,development,tool
Classifier: Development Status :: 3 - Alpha
Classifier: Intended Audience :: Information Technology
Classifier: Topic :: Software Development
Classifier: Topic :: Software Development :: Documentation
Classifier: License :: OSI Approved :: GNU General Public License v3 (GPLv3)
Classifier: Programming Language :: Python :: 3
Requires-Python: >=3.10, <4
Provides-Extra: dev
Requires-Dist: check-manifest; extra == "dev"
Provides-Extra: test
Requires-Dist: coverage; extra == "test"
Dynamic: author
Dynamic: author-email
Dynamic: classifier
Dynamic: description
Dynamic: description-content-type
Dynamic: home-page
Dynamic: keywords
Dynamic: license
Dynamic: project-url
Dynamic: provides-extra
Dynamic: requires-python
Dynamic: summary
